trace_to_log/__init__.py
trace_to_log/py.typed
trace_to_log-0.2.0.dist-info/WHEEL
trace_to_log-0.2.0.dist-info/METADATA
trace_to_log-0.2.0.dist-info/RECORD
