Metadata-Version: 2.4
Name: trace-to-log
Version: 0.2.0
Summary: Add minimal tracing to a function using a decorator
Author: Greg
Author-email: Greg <trace_to_log@fastmail.com>
License-Expression: MIT
Requires-Python: >=3.8
Project-URL: Repository, https://github.com/mentaal/trace-to-log
